{"nodes": [{"id": "run_main", "label": "run.main", "file_type": "code", "source_file": "run.py", "source_location": "def main", "source_url": null, "captured_at": null, "author": null, "contributor": null}, {"id": "run_install_deps", "label": "install_deps", "file_type": "code", "source_file": "run.py", "source_location": "def install_deps", "source_url": null, "captured_at": null, "author": null, "contributor": null}], "edges": [{"source": "run_main", "target": "server_main", "relation": "calls", "confidence": "EXTRACTED", "confidence_score": 1.0, "source_file": "run.py", "source_location": "def main", "weight": 1.0}, {"source": "run_main", "target": "run_install_deps", "relation": "calls", "confidence": "EXTRACTED", "confidence_score": 1.0, "source_file": "run.py", "source_location": "def main", "weight": 1.0}], "hyperedges": []}